csv_export_gsheets/__init__.py
csv_export_gsheets/__main__.py
csv_export_gsheets/gsheet.py
csv_export_gsheets/utils/__init__.py
csv_export_gsheets/utils/conf.py
csv_export_gsheets/utils/credentials.py
csv_export_gsheets-0.0.13.dist-info/LICENSE
csv_export_gsheets-0.0.13.dist-info/METADATA
csv_export_gsheets-0.0.13.dist-info/WHEEL
csv_export_gsheets-0.0.13.dist-info/entry_points.txt
csv_export_gsheets-0.0.13.dist-info/top_level.txt
csv_export_gsheets-0.0.13.dist-info/RECORD
