Metadata-Version: 2.1
Name: csv-export-gsheets
Version: 0.0.13
Summary: Export CSV files to Google Spreadsheets
Home-page: https://github.com/dlancer/csv-export-gsheets
Author: dlancer
Author-email: dmdpost@gmail.com
Maintainer: dlancer
Maintainer-email: dmdpost@gmail.com
License: BSD
Platform: UNKNOWN
Classifier: Environment :: Web Environment
Classifier: Framework :: Django
Classifier: Intended Audience :: Developers
Classifier: License :: OSI Approved :: BSD License
Classifier: Operating System :: OS Independent
Classifier: Programming Language :: Python
Classifier: Programming Language :: Python :: 3.6
Classifier: Programming Language :: Python :: 3.7
Classifier: Topic :: Internet :: WWW/HTTP
Classifier: Topic :: Internet :: WWW/HTTP :: Dynamic Content
Classifier: Development Status :: 3 - Alpha
Requires-Python: >=3.6
Requires-Dist: certifi
Requires-Dist: chardet
Requires-Dist: gspread
Requires-Dist: httplib2
Requires-Dist: idna
Requires-Dist: oauth2client
Requires-Dist: pyasn1
Requires-Dist: pyasn1-modules
Requires-Dist: requests
Requires-Dist: rsa
Requires-Dist: six
Requires-Dist: urllib3
Provides-Extra: test
Requires-Dist: atomicwrites ; extra == 'test'
Requires-Dist: attrs ; extra == 'test'
Requires-Dist: coverage ; extra == 'test'
Requires-Dist: entrypoints ; extra == 'test'
Requires-Dist: flake8 ; extra == 'test'
Requires-Dist: isort ; extra == 'test'
Requires-Dist: mccabe ; extra == 'test'
Requires-Dist: more-itertools ; extra == 'test'
Requires-Dist: pluggy ; extra == 'test'
Requires-Dist: py ; extra == 'test'
Requires-Dist: pycodestyle ; extra == 'test'
Requires-Dist: pyflakes ; extra == 'test'
Requires-Dist: pygments ; extra == 'test'
Requires-Dist: pytest ; extra == 'test'
Requires-Dist: pytest-cov ; extra == 'test'
Requires-Dist: six ; extra == 'test'
Requires-Dist: v ; extra == 'test'
Requires-Dist: wcwidth ; extra == 'test'
